stackl/__init__.py
stackl/errors.py
stackl/events.py
stackl/helpers.py
stackl/models.py
stackl/tasks.py
stackl/wsclient.py
stat/__init__.py
stackl-0.0.5.dist-info/LICENSE.md
stackl-0.0.5.dist-info/METADATA
stackl-0.0.5.dist-info/WHEEL
stackl-0.0.5.dist-info/top_level.txt
stackl-0.0.5.dist-info/RECORD
