Metadata-Version: 2.1
Name: stackl
Version: 0.0.5
Summary: Python library for connecting to Stack Exchange chat
Home-page: https://github.com/ArtOfCode-/stackl
Author: ArtOfCode
Author-email: hello@artofcode.co.uk
License: UNKNOWN
Platform: UNKNOWN
Classifier: Programming Language :: Python :: 3
Classifier: License :: OSI Approved :: MIT License
Classifier: Operating System :: OS Independent
